fasttrimmatic/__init__.py
fasttrimmatic/fasttrimmatic.py
fasttrimmatic-1.0.0.dist-info/licenses/LICENSE
fasttrimmatic-1.0.0.dist-info/METADATA
fasttrimmatic-1.0.0.dist-info/WHEEL
fasttrimmatic-1.0.0.dist-info/entry_points.txt
fasttrimmatic-1.0.0.dist-info/top_level.txt
fasttrimmatic-1.0.0.dist-info/RECORD
