Metadata-Version: 2.4
Name: fasttrimmatic
Version: 1.0.0
Summary: Hybrid fastp + Trimmomatic-like FASTQ quality control and trimming tool
Home-page: https://github.com/bbeckley-hub/fasttrimmatic
Author: Beckley Brown
Author-email: brownbeckley94@gmail.com
Project-URL: Bug Tracker, https://github.com/bbeckley-hub/fasttrimmatic/issues
Project-URL: Documentation, https://github.com/bbeckley-hub/fasttrimmatic#readme
Classifier: Programming Language :: Python :: 3
Classifier: License :: OSI Approved :: MIT License
Classifier: Operating System :: OS Independent
Classifier: Topic :: Scientific/Engineering :: Bio-Informatics
Requires-Python: >=3.7
License-File: LICENSE
Requires-Dist: biopython
Requires-Dist: numpy
Requires-Dist: tqdm
Provides-Extra: ml
Requires-Dist: scikit-learn; extra == "ml"
Dynamic: author
Dynamic: author-email
Dynamic: classifier
Dynamic: description
Dynamic: description-content-type
Dynamic: home-page
Dynamic: license-file
Dynamic: project-url
Dynamic: provides-extra
Dynamic: requires-dist
Dynamic: requires-python
Dynamic: summary
